tug_overlap_checker/__init__.py
tug_overlap_checker/tug_overlap_checker.py
tug_overlap_checker-1.0.4.dist-info/LICENSE
tug_overlap_checker-1.0.4.dist-info/METADATA
tug_overlap_checker-1.0.4.dist-info/WHEEL
tug_overlap_checker-1.0.4.dist-info/entry_points.txt
tug_overlap_checker-1.0.4.dist-info/top_level.txt
tug_overlap_checker-1.0.4.dist-info/RECORD
