Metadata-Version: 2.1
Name: tug-overlap-checker
Version: 1.0.4
Summary: Check for course overlaps at Graz University of Technology
Home-page: https://github.com/lolei/tug-overlap-checker
Author: Lorenz Leitner
Author-email: lrnz.ltnr@gmail.com
License: UNKNOWN
Platform: UNKNOWN
Classifier: Programming Language :: Python :: 3.8
Classifier: License :: OSI Approved :: MIT License
Classifier: Operating System :: OS Independent
Requires-Python: >=3
Requires-Dist: bs4
Requires-Dist: selenium
